{"nodes":[{"label":"Wildlife Spectacle","x":183.44837951660156,"y":-106.03057098388672,"id":"50","attributes":{"natural england(simon christian)":"2","yorkshire water(miranda foster)":"2","yorkshire wildlife trust (kevin bayes)":"2","importance":"0","﻿id":"47","out-degree":"0","degree":"0","eccentricity":"0.0","closeness centrality":"0.0","eigenvector centrality":"0.0","barmby on marsh pc(david pridmore)":"0","controllability":"2","catchment management partnership(karen saunders)":"1","nfu (lucinda douglas)":"2","in-degree":"0","environment agency(mark reid, tom paggett)":"1","betweenness centrality":"0.0","east yorkshire rivers trust (karen saunders)":"1"},"color":"rgb(0,0,0)","size":10.0},{"label":"Loftsome Bridge WTW infrastructure (Screens)","x":-366.5940856933594,"y":332.43084716796875,"id":"38","attributes":{"natural england(simon christian)":"1","yorkshire water(miranda foster)":"3","yorkshire wildlife trust (kevin bayes)":"1","importance":"0","﻿id":"9","out-degree":"2","degree":"3","eccentricity":"5.0","closeness centrality":"3.4242425","eigenvector centrality":"0.12788787","barmby on marsh pc(david pridmore)":"0","controllability":"1","catchment management partnership(karen saunders)":"1","nfu (lucinda douglas)":"1","in-degree":"1","environment agency(mark reid, tom paggett)":"1","betweenness centrality":"0.0","east yorkshire rivers trust (karen saunders)":"1"},"color":"rgb(0,0,0)","size":10.0},{"label":"*Habitat and species:meadows","x":392.3167724609375,"y":-340.36468505859375,"id":"6","attributes":{"natural england(simon christian)":"2","yorkshire water(miranda foster)":"1","yorkshire wildlife trust (kevin bayes)":"2","importance":"1","﻿id":"32","out-degree":"3","degree":"13","eccentricity":"6.0","closeness centrality":"3.4848485","eigenvector centrality":"0.8065912","barmby on marsh pc(david pridmore)":"0","controllability":"1","catchment management partnership(karen saunders)":"1","nfu (lucinda douglas)":"2","in-degree":"10","environment agency(mark reid, tom paggett)":"1","betweenness centrality":"250.23334","east yorkshire rivers trust (karen saunders)":"1"},"color":"rgb(0,0,0)","size":10.0},{"label":"Maintain water level Loftsome B","x":-271.5999450683594,"y":220.88026428222656,"id":"40","attributes":{"natural england(simon christian)":"2","yorkshire water(miranda foster)":"1","yorkshire wildlife trust (kevin bayes)":"1","importance":"0","﻿id":"8","out-degree":"1","degree":"2","eccentricity":"5.0","closeness centrality":"3.5151515","eigenvector centrality":"0.1348658","barmby on marsh pc(david pridmore)":"0","controllability":"1","catchment management partnership(karen saunders)":"1","nfu (lucinda douglas)":"1","in-degree":"1","environment agency(mark reid, tom paggett)":"3","betweenness centrality":"18.832144","east yorkshire rivers trust (karen saunders)":"1"},"color":"rgb(0,0,0)","size":10.0},{"label":"Maintain navigation water level","x":-421.59912109375,"y":-469.4677429199219,"id":"39","attributes":{"natural england(simon christian)":"2","yorkshire water(miranda foster)":"1","yorkshire wildlife trust (kevin bayes)":"1","importance":"0","﻿id":"25","out-degree":"2","degree":"3","eccentricity":"8.0","closeness centrality":"5.090909","eigenvector centrality":"0.1348658","barmby on marsh pc(david pridmore)":"0","controllability":"1","catchment management partnership(karen saunders)":"1","nfu (lucinda douglas)":"1","in-degree":"1","environment agency(mark reid, tom paggett)":"3","betweenness centrality":"35.0","east yorkshire rivers trust (karen saunders)":"1"},"color":"rgb(0,0,0)","size":10.0},{"label":"Lateral Connectivity","x":-398.5030517578125,"y":-162.94586181640625,"id":"37","attributes":{"natural england(simon christian)":"2","yorkshire water(miranda foster)":"1","yorkshire wildlife trust (kevin bayes)":"1","importance":"0","﻿id":"45","out-degree":"2","degree":"2","eccentricity":"7.0","closeness centrality":"4.2058825","eigenvector centrality":"0.0","barmby on marsh pc(david pridmore)":"0","controllability":"1","catchment management partnership(karen saunders)":"1","nfu (lucinda douglas)":"1","in-degree":"0","environment agency(mark reid, tom paggett)":"2","betweenness centrality":"0.0","east yorkshire rivers trust (karen saunders)":"1"},"color":"rgb(0,0,0)","size":10.0},{"label":"Fisheries: abundance","x":50.70403289794922,"y":309.90087890625,"id":"28","attributes":{"natural england(simon christian)":"1","yorkshire water(miranda foster)":"2","yorkshire wildlife trust (kevin bayes)":"1","importance":"0","﻿id":"12","out-degree":"1","degree":"6","eccentricity":"8.0","closeness centrality":"5.242424","eigenvector centrality":"0.5161856","barmby on marsh pc(david pridmore)":"0","controllability":"1","catchment management partnership(karen saunders)":"1","nfu (lucinda douglas)":"2","in-degree":"5","environment agency(mark reid, tom paggett)":"2","betweenness centrality":"90.71429","east yorkshire rivers trust (karen saunders)":"1"},"color":"rgb(0,0,0)","size":10.0},{"label":"Diffuse Pollution","x":-290.6092834472656,"y":423.20135498046875,"id":"22","attributes":{"natural england(simon christian)":"0","yorkshire water(miranda foster)":"0","yorkshire wildlife trust (kevin bayes)":"0","importance":"0","﻿id":"46","out-degree":"0","degree":"0","eccentricity":"0.0","closeness centrality":"0.0","eigenvector centrality":"0.0","barmby on marsh pc(david pridmore)":"0","controllability":"0","catchment management partnership(karen saunders)":"1","nfu (lucinda douglas)":"0","in-degree":"0","environment agency(mark reid, tom paggett)":"0","betweenness centrality":"0.0","east yorkshire rivers trust (karen saunders)":"1"},"color":"rgb(0,0,0)","size":10.0},{"label":"*Water abstraction for agriculture","x":163.19964599609375,"y":373.16424560546875,"id":"13","attributes":{"natural england(simon christian)":"1","yorkshire water(miranda foster)":"1","yorkshire wildlife trust (kevin bayes)":"1","importance":"1","﻿id":"37","out-degree":"1","degree":"6","eccentricity":"5.0","closeness centrality":"3.121212","eigenvector centrality":"0.28819776","barmby on marsh pc(david pridmore)":"0","controllability":"1","catchment management partnership(karen saunders)":"1","nfu (lucinda douglas)":"2","in-degree":"5","environment agency(mark reid, tom paggett)":"2","betweenness centrality":"27.428572","east yorkshire rivers trust (karen saunders)":"1"},"color":"rgb(0,0,0)","size":10.0},{"label":"Connectedness of Canal and Navigable River","x":-388.5765380859375,"y":-420.7832946777344,"id":"21","attributes":{"natural england(simon christian)":"0","yorkshire water(miranda foster)":"0","yorkshire wildlife trust (kevin bayes)":"0","importance":"0","﻿id":"49","out-degree":"0","degree":"0","eccentricity":"0.0","closeness centrality":"0.0","eigenvector centrality":"0.0","barmby on marsh pc(david pridmore)":"0","controllability":"0","catchment management partnership(karen saunders)":"0","nfu (lucinda douglas)":"0","in-degree":"0","environment agency(mark reid, tom paggett)":"0","betweenness centrality":"0.0","east yorkshire rivers trust (karen saunders)":"0"},"color":"rgb(0,0,0)","size":10.0},{"label":"Social History","x":323.4391174316406,"y":-385.3293151855469,"id":"47","attributes":{"natural england(simon christian)":"1","yorkshire water(miranda foster)":"1","yorkshire wildlife trust (kevin bayes)":"1","importance":"0","﻿id":"44","out-degree":"0","degree":"0","eccentricity":"0.0","closeness centrality":"0.0","eigenvector centrality":"0.0","barmby on marsh pc(david pridmore)":"0","controllability":"1","catchment management partnership(karen saunders)":"1","nfu (lucinda douglas)":"1","in-degree":"0","environment agency(mark reid, tom paggett)":"2","betweenness centrality":"0.0","east yorkshire rivers trust (karen saunders)":"1"},"color":"rgb(0,0,0)","size":10.0},{"label":"*Built development","x":-102.7729263305664,"y":204.13336181640625,"id":"1","attributes":{"natural england(simon christian)":"2","yorkshire water(miranda foster)":"2","yorkshire wildlife trust (kevin bayes)":"2","importance":"1","﻿id":"24","out-degree":"0","degree":"2","eccentricity":"0.0","closeness centrality":"0.0","eigenvector centrality":"0.1694855","barmby on marsh pc(david pridmore)":"0","controllability":"2","catchment management partnership(karen saunders)":"1","nfu (lucinda douglas)":"1","in-degree":"2","environment agency(mark reid, tom paggett)":"2","betweenness centrality":"0.0","east yorkshire rivers trust (karen saunders)":"1"},"color":"rgb(0,0,0)","size":10.0},{"label":"Historic Landscape","x":-358.2112121582031,"y":-299.2930908203125,"id":"34","attributes":{"natural england(simon christian)":"2","yorkshire water(miranda foster)":"1","yorkshire wildlife trust (kevin bayes)":"1","importance":"0","﻿id":"42","out-degree":"0","degree":"0","eccentricity":"0.0","closeness centrality":"0.0","eigenvector centrality":"0.0","barmby on marsh pc(david pridmore)":"0","controllability":"1","catchment management partnership(karen saunders)":"1","nfu (lucinda douglas)":"1","in-degree":"0","environment agency(mark reid, tom paggett)":"1","betweenness centrality":"0.0","east yorkshire rivers trust (karen saunders)":"1"},"color":"rgb(0,0,0)","size":10.0},{"label":"Funding","x":535.3302001953125,"y":-322.72955322265625,"id":"32","attributes":{"natural england(simon christian)":"2","yorkshire water(miranda foster)":"2","yorkshire wildlife trust (kevin bayes)":"2","importance":"0","﻿id":"27","out-degree":"6","degree":"12","eccentricity":"4.0","closeness centrality":"2.2121212","eigenvector centrality":"0.69001776","barmby on marsh pc(david pridmore)":"0","controllability":"2","catchment management partnership(karen saunders)":"1","nfu (lucinda douglas)":"1","in-degree":"6","environment agency(mark reid, tom paggett)":"2","betweenness centrality":"677.875","east yorkshire rivers trust (karen saunders)":"1"},"color":"rgb(0,0,0)","size":10.0},{"label":"Overhanging trees (RC navigation)","x":433.9779968261719,"y":-6.837973594665527,"id":"42","attributes":{"natural england(simon christian)":"2","yorkshire water(miranda foster)":"1","yorkshire wildlife trust (kevin bayes)":"2","importance":"0","﻿id":"28","out-degree":"5","degree":"8","eccentricity":"7.0","closeness centrality":"4.0","eigenvector centrality":"0.23830348","barmby on marsh pc(david pridmore)":"0","controllability":"1","catchment management partnership(karen saunders)":"1","nfu (lucinda douglas)":"2","in-degree":"3","environment agency(mark reid, tom paggett)":"1","betweenness centrality":"49.407143","east yorkshire rivers trust (karen saunders)":"1"},"color":"rgb(0,0,0)","size":10.0},{"label":"Landscape","x":-135.39584350585938,"y":444.3006591796875,"id":"36","attributes":{"natural england(simon christian)":"1","yorkshire water(miranda foster)":"1","yorkshire wildlife trust (kevin bayes)":"1","importance":"0","﻿id":"43","out-degree":"0","degree":"0","eccentricity":"0.0","closeness centrality":"0.0","eigenvector centrality":"0.0","barmby on marsh pc(david pridmore)":"0","controllability":"1","catchment management partnership(karen saunders)":"1","nfu (lucinda douglas)":"1","in-degree":"0","environment agency(mark reid, tom paggett)":"1","betweenness centrality":"0.0","east yorkshire rivers trust (karen saunders)":"1"},"color":"rgb(0,0,0)","size":10.0},{"label":"Sediment: Lower Derwent","x":457.8540344238281,"y":258.30908203125,"id":"46","attributes":{"natural england(simon christian)":"1","yorkshire water(miranda foster)":"1","yorkshire wildlife trust (kevin bayes)":"1","importance":"0","﻿id":"1","out-degree":"4","degree":"6","eccentricity":"5.0","closeness centrality":"3.030303","eigenvector centrality":"0.17788436","barmby on marsh pc(david pridmore)":"0","controllability":"1","catchment management partnership(karen saunders)":"1","nfu (lucinda douglas)":"2","in-degree":"2","environment agency(mark reid, tom paggett)":"2","betweenness centrality":"26.969048"},"color":"rgb(0,0,0)","size":10.0},{"label":"*Traditional management","x":-310.06787109375,"y":356.34442138671875,"id":"11","attributes":{"natural england(simon christian)":"3","yorkshire water(miranda foster)":"1","yorkshire wildlife trust (kevin bayes)":"2","importance":"1","﻿id":"31","out-degree":"1","degree":"4","eccentricity":"7.0","closeness centrality":"4.3939395","eigenvector centrality":"0.4410953","barmby on marsh pc(david pridmore)":"0","controllability":"2","catchment management partnership(karen saunders)":"1","nfu (lucinda douglas)":"2","in-degree":"3","environment agency(mark reid, tom paggett)":"2","betweenness centrality":"1.1190476","east yorkshire rivers trust (karen saunders)":"1"},"color":"rgb(0,0,0)","size":10.0},{"label":"Abstraction licence volume (constant)","x":453.55908203125,"y":-413.68292236328125,"id":"14","attributes":{"natural england(simon christian)":"1","yorkshire water(miranda foster)":"2","yorkshire wildlife trust (kevin bayes)":"1","importance":"0","﻿id":"10","out-degree":"1","degree":"1","eccentricity":"5.0","closeness centrality":"3.5294118","eigenvector centrality":"0.0","barmby on marsh pc(david pridmore)":"0","controllability":"1","catchment management partnership(karen saunders)":"1","nfu (lucinda douglas)":"2","in-degree":"0","environment agency(mark reid, tom paggett)":"2","betweenness centrality":"0.0","east yorkshire rivers trust (karen saunders)":"1"},"color":"rgb(0,0,0)","size":10.0},{"label":"Impact of navigation levels on gravity outlets","x":165.0902099609375,"y":-374.9195556640625,"id":"35","attributes":{"natural england(simon christian)":"1","yorkshire water(miranda foster)":"1","yorkshire wildlife trust (kevin bayes)":"1","importance":"0","﻿id":"26","out-degree":"1","degree":"2","eccentricity":"7.0","closeness centrality":"4.3333335","eigenvector centrality":"0.049489956","barmby on marsh pc(david pridmore)":"0","controllability":"1","catchment management partnership(karen saunders)":"1","nfu (lucinda douglas)":"1","in-degree":"1","environment agency(mark reid, tom paggett)":"1","betweenness centrality":"31.0","east yorkshire rivers trust (karen saunders)":"1"},"color":"rgb(0,0,0)","size":10.0},{"label":"*Walking","x":-258.4566650390625,"y":-192.68768310546875,"id":"12","attributes":{"natural england(simon christian)":"2","yorkshire water(miranda foster)":"1","yorkshire wildlife trust (kevin bayes)":"2","importance":"1","﻿id":"18","out-degree":"1","degree":"4","eccentricity":"8.0","closeness centrality":"5.242424","eigenvector centrality":"0.6410476","barmby on marsh pc(david pridmore)":"0","controllability":"1","catchment management partnership(karen saunders)":"1","nfu (lucinda douglas)":"2","in-degree":"3","environment agency(mark reid, tom paggett)":"1","betweenness centrality":"4.202381","east yorkshire rivers trust (karen saunders)":"1"},"color":"rgb(0,0,0)","size":10.0},{"label":"Navigation Access Issues","x":-346.78619384765625,"y":-6.498312950134277,"id":"41","attributes":{"natural england(simon christian)":"0","yorkshire water(miranda foster)":"0","yorkshire wildlife trust (kevin bayes)":"0","importance":"0","﻿id":"48","out-degree":"0","degree":"0","eccentricity":"0.0","closeness centrality":"0.0","eigenvector centrality":"0.0","barmby on marsh pc(david pridmore)":"0","controllability":"0","catchment management partnership(karen saunders)":"0","nfu (lucinda douglas)":"0","in-degree":"0","environment agency(mark reid, tom paggett)":"0","betweenness centrality":"0.0","east yorkshire rivers trust (karen saunders)":"0"},"color":"rgb(0,0,0)","size":10.0},{"label":"Everyday wildlife","x":269.93524169921875,"y":97.25769805908203,"id":"27","attributes":{"natural england(simon christian)":"1","yorkshire water(miranda foster)":"1","yorkshire wildlife trust (kevin bayes)":"1","importance":"0","﻿id":"34","out-degree":"1","degree":"4","eccentricity":"6.0","closeness centrality":"3.7575758","eigenvector centrality":"0.51085514","barmby on marsh pc(david pridmore)":"0","controllability":"1","catchment management partnership(karen saunders)":"1","nfu (lucinda douglas)":"2","in-degree":"3","environment agency(mark reid, tom paggett)":"2","betweenness centrality":"0.78333336","east yorkshire rivers trust (karen saunders)":"1"},"color":"rgb(0,0,0)","size":10.0},{"label":"Disturbance","x":-277.466064453125,"y":-154.60433959960938,"id":"23","attributes":{"natural england(simon christian)":"1","yorkshire water(miranda foster)":"1","yorkshire wildlife trust (kevin bayes)":"2","importance":"0","﻿id":"22","out-degree":"2","degree":"6","eccentricity":"7.0","closeness centrality":"4.3030305","eigenvector centrality":"0.57223254","barmby on marsh pc(david pridmore)":"0","controllability":"1","catchment management partnership(karen saunders)":"1","nfu (lucinda douglas)":"1","in-degree":"4","environment agency(mark reid, tom paggett)":"1","betweenness centrality":"58.816666","east yorkshire rivers trust (karen saunders)":"1"},"color":"rgb(0,0,0)","size":10.0},{"label":"Water Quality: Lower Derwent","x":-57.60642623901367,"y":192.92628479003906,"id":"49","attributes":{"natural england(simon christian)":"1","yorkshire water(miranda foster)":"1","yorkshire wildlife trust (kevin bayes)":"1","importance":"0","﻿id":"2","out-degree":"4","degree":"5","eccentricity":"5.0","closeness centrality":"3.030303","eigenvector centrality":"0.12903437","barmby on marsh pc(david pridmore)":"0","controllability":"1","catchment management partnership(karen saunders)":"1","nfu (lucinda douglas)":"2","in-degree":"1","environment agency(mark reid, tom paggett)":"2","betweenness centrality":"24.683332","east yorkshire rivers trust (karen saunders)":"1"},"color":"rgb(0,0,0)","size":10.0},{"label":"Saline intrusion prevention","x":-390.86968994140625,"y":-73.73018646240234,"id":"45","attributes":{"natural england(simon christian)":"1","yorkshire water(miranda foster)":"1","yorkshire wildlife trust (kevin bayes)":"1","importance":"0","﻿id":"5","out-degree":"1","degree":"2","eccentricity":"5.0","closeness centrality":"3.5151515","eigenvector centrality":"0.1348658","barmby on marsh pc(david pridmore)":"0","controllability":"1","catchment management partnership(karen saunders)":"1","nfu (lucinda douglas)":"2","in-degree":"1","environment agency(mark reid, tom paggett)":"3","betweenness centrality":"18.832144","east yorkshire rivers trust (karen saunders)":"1"},"color":"rgb(0,0,0)","size":10.0},{"label":"*Drinking water abstraction (Loftsome B/E\u0027ton)","x":-240.297607421875,"y":62.55622100830078,"id":"2","attributes":{"natural england(simon christian)":"1","yorkshire water(miranda foster)":"3","yorkshire wildlife trust (kevin bayes)":"1","importance":"1","﻿id":"7","out-degree":"5","degree":"13","eccentricity":"4.0","closeness centrality":"2.6060605","eigenvector centrality":"0.3158249","barmby on marsh pc(david pridmore)":"0","controllability":"1","catchment management partnership(karen saunders)":"1","nfu (lucinda douglas)":"1","in-degree":"8","environment agency(mark reid, tom paggett)":"2","betweenness centrality":"232.0738","east yorkshire rivers trust (karen saunders)":"1"},"color":"rgb(0,0,0)","size":10.0},{"label":"Rainfall (climate)","x":224.34437561035156,"y":219.5491485595703,"id":"44","attributes":{"natural england(simon christian)":"1","yorkshire water(miranda foster)":"1","yorkshire wildlife trust (kevin bayes)":"1","importance":"0","﻿id":"4","out-degree":"1","degree":"1","eccentricity":"5.0","closeness centrality":"3.0294118","eigenvector centrality":"0.0","barmby on marsh pc(david pridmore)":"0","controllability":"1","catchment management partnership(karen saunders)":"1","nfu (lucinda douglas)":"0","in-degree":"0","environment agency(mark reid, tom paggett)":"0","betweenness centrality":"0.0","east yorkshire rivers trust (karen saunders)":"0"},"color":"rgb(0,0,0)","size":10.0},{"label":"Barmby Parliament Act-Nav levels","x":409.99603271484375,"y":206.09033203125,"id":"19","attributes":{"natural england(simon christian)":"2","yorkshire water(miranda foster)":"1","yorkshire wildlife trust (kevin bayes)":"1","importance":"0","﻿id":"11","out-degree":"2","degree":"3","eccentricity":"4.0","closeness centrality":"2.7575758","eigenvector centrality":"0.12788787","barmby on marsh pc(david pridmore)":"0","controllability":"1","catchment management partnership(karen saunders)":"1","nfu (lucinda douglas)":"1","in-degree":"1","environment agency(mark reid, tom paggett)":"1","betweenness centrality":"29.833334","east yorkshire rivers trust (karen saunders)":"1"},"color":"rgb(0,0,0)","size":10.0},{"label":"Barmby Barrage: Structure and operation","x":61.03435516357422,"y":-359.92791748046875,"id":"18","attributes":{"natural england(simon christian)":"2","yorkshire water(miranda foster)":"1","yorkshire wildlife trust (kevin bayes)":"1","importance":"0","﻿id":"6","out-degree":"8","degree":"12","eccentricity":"3.0","closeness centrality":"2.121212","eigenvector centrality":"0.3721223","barmby on marsh pc(david pridmore)":"0","controllability":"1","catchment management partnership(karen saunders)":"1","nfu (lucinda douglas)":"1","in-degree":"4","environment agency(mark reid, tom paggett)":"3","betweenness centrality":"312.35834","east yorkshire rivers trust (karen saunders)":"1"},"color":"rgb(0,0,0)","size":10.0},{"label":"*Public access","x":435.9569091796875,"y":501.2388916015625,"id":"10","attributes":{"natural england(simon christian)":"2","yorkshire water(miranda foster)":"1","yorkshire wildlife trust (kevin bayes)":"2","importance":"1","﻿id":"19","out-degree":"5","degree":"6","eccentricity":"6.0","closeness centrality":"3.4545455","eigenvector centrality":"0.28220615","barmby on marsh pc(david pridmore)":"0","controllability":"1","catchment management partnership(karen saunders)":"1","nfu (lucinda douglas)":"2","in-degree":"1","environment agency(mark reid, tom paggett)":"1","betweenness centrality":"38.42381","east yorkshire rivers trust (karen saunders)":"1"},"color":"rgb(0,0,0)","size":10.0},{"label":"Tranquility","x":-195.3506622314453,"y":59.99036407470703,"id":"48","attributes":{"natural england(simon christian)":"2","yorkshire water(miranda foster)":"1","yorkshire wildlife trust (kevin bayes)":"1","importance":"0","﻿id":"20","out-degree":"3","degree":"6","eccentricity":"6.0","closeness centrality":"3.6969697","eigenvector centrality":"0.7033631","barmby on marsh pc(david pridmore)":"0","controllability":"1","catchment management partnership(karen saunders)":"1","nfu (lucinda douglas)":"2","in-degree":"3","environment agency(mark reid, tom paggett)":"1","betweenness centrality":"136.9762","east yorkshire rivers trust (karen saunders)":"1"},"color":"rgb(0,0,0)","size":10.0},{"label":"Bank Management","x":-72.57917022705078,"y":87.41962432861328,"id":"17","attributes":{"natural england(simon christian)":"2","yorkshire water(miranda foster)":"1","yorkshire wildlife trust (kevin bayes)":"1","importance":"0","﻿id":"40","out-degree":"0","degree":"0","eccentricity":"0.0","closeness centrality":"0.0","eigenvector centrality":"0.0","barmby on marsh pc(david pridmore)":"0","controllability":"1","catchment management partnership(karen saunders)":"1","nfu (lucinda douglas)":"2","in-degree":"0","environment agency(mark reid, tom paggett)":"2","betweenness centrality":"0.0","east yorkshire rivers trust (karen saunders)":"1"},"color":"rgb(0,0,0)","size":10.0},{"label":"*Longitudinal connectivity","x":446.1895751953125,"y":-51.65380096435547,"id":"8","attributes":{"natural england(simon christian)":"2","yorkshire water(miranda foster)":"1","yorkshire wildlife trust (kevin bayes)":"1","importance":"1","﻿id":"14","out-degree":"1","degree":"2","eccentricity":"10.0","closeness centrality":"6.818182","eigenvector centrality":"0.1348658","barmby on marsh pc(david pridmore)":"0","controllability":"1","catchment management partnership(karen saunders)":"1","nfu (lucinda douglas)":"1","in-degree":"1","environment agency(mark reid, tom paggett)":"1","betweenness centrality":"34.0","east yorkshire rivers trust (karen saunders)":"1"},"color":"rgb(0,0,0)","size":10.0},{"label":"*Fishing","x":362.655029296875,"y":-348.82861328125,"id":"4","attributes":{"natural england(simon christian)":"2","yorkshire water(miranda foster)":"1","yorkshire wildlife trust (kevin bayes)":"1","importance":"1","﻿id":"21","out-degree":"2","degree":"6","eccentricity":"7.0","closeness centrality":"4.3939395","eigenvector centrality":"0.592105","barmby on marsh pc(david pridmore)":"0","controllability":"2","catchment management partnership(karen saunders)":"1","nfu (lucinda douglas)":"2","in-degree":"4","environment agency(mark reid, tom paggett)":"2","betweenness centrality":"112.94762","east yorkshire rivers trust (karen saunders)":"2"},"color":"rgb(0,0,0)","size":10.0},{"label":"*Fish migration","x":96.68346405029297,"y":255.370849609375,"id":"3","attributes":{"natural england(simon christian)":"0","yorkshire water(miranda foster)":"2","yorkshire wildlife trust (kevin bayes)":"1","importance":"1","﻿id":"13","out-degree":"1","degree":"3","eccentricity":"9.0","closeness centrality":"6.030303","eigenvector centrality":"0.052807074","barmby on marsh pc(david pridmore)":"0","controllability":"1","catchment management partnership(karen saunders)":"1","nfu (lucinda douglas)":"1","in-degree":"2","environment agency(mark reid, tom paggett)":"2","betweenness centrality":"32.333332","east yorkshire rivers trust (karen saunders)":"1"},"color":"rgb(0,0,0)","size":10.0},{"label":"Flooding:Timing/duration/amplitude","x":-16.784095764160156,"y":195.27410888671875,"id":"30","attributes":{"natural england(simon christian)":"1","yorkshire water(miranda foster)":"1","yorkshire wildlife trust (kevin bayes)":"1","importance":"0","﻿id":"36","out-degree":"2","degree":"3","eccentricity":"4.0","closeness centrality":"2.6969697","eigenvector centrality":"0.0635335","barmby on marsh pc(david pridmore)":"0","controllability":"1","catchment management partnership(karen saunders)":"1","nfu (lucinda douglas)":"1","in-degree":"1","environment agency(mark reid, tom paggett)":"1","betweenness centrality":"7.457143","east yorkshire rivers trust (karen saunders)":"1"},"color":"rgb(0,0,0)","size":10.0},{"label":"*Flood management","x":568.7052612304688,"y":-428.7215881347656,"id":"5","attributes":{"natural england(simon christian)":"1","yorkshire water(miranda foster)":"1","yorkshire wildlife trust (kevin bayes)":"1","importance":"1","﻿id":"23","out-degree":"2","degree":"4","eccentricity":"8.0","closeness centrality":"4.7272725","eigenvector centrality":"0.30718023","barmby on marsh pc(david pridmore)":"0","controllability":"1","catchment management partnership(karen saunders)":"1","nfu (lucinda douglas)":"2","in-degree":"2","environment agency(mark reid, tom paggett)":"2","betweenness centrality":"50.935715","east yorkshire rivers trust (karen saunders)":"1"},"color":"rgb(0,0,0)","size":10.0},{"label":"Habitat directive/WFD/CRoW (?) act","x":-38.80261993408203,"y":-430.5906677246094,"id":"33","attributes":{"natural england(simon christian)":"3","yorkshire water(miranda foster)":"1","yorkshire wildlife trust (kevin bayes)":"1","importance":"0","﻿id":"35","out-degree":"6","degree":"6","eccentricity":"5.0","closeness centrality":"2.5882354","eigenvector centrality":"0.0","barmby on marsh pc(david pridmore)":"0","controllability":"1","catchment management partnership(karen saunders)":"1","nfu (lucinda douglas)":"1","in-degree":"0","environment agency(mark reid, tom paggett)":"2","betweenness centrality":"0.0","east yorkshire rivers trust (karen saunders)":"1"},"color":"rgb(0,0,0)","size":10.0},{"label":"Drainage: Local Area and Upper Catchment","x":-53.98578643798828,"y":-117.66283416748047,"id":"25","attributes":{"natural england(simon christian)":"1","yorkshire water(miranda foster)":"1","yorkshire wildlife trust (kevin bayes)":"1","importance":"0","﻿id":"51","out-degree":"0","degree":"0","eccentricity":"0.0","closeness centrality":"0.0","eigenvector centrality":"0.0","barmby on marsh pc(david pridmore)":"0","controllability":"1","catchment management partnership(karen saunders)":"1","nfu (lucinda douglas)":"1","in-degree":"0","environment agency(mark reid, tom paggett)":"2","betweenness centrality":"0.0","east yorkshire rivers trust (karen saunders)":"1"},"color":"rgb(0,0,0)","size":10.0},{"label":"Flows: Lower Derwent","x":-341.19586181640625,"y":294.994384765625,"id":"31","attributes":{"natural england(simon christian)":"1","yorkshire water(miranda foster)":"1","yorkshire wildlife trust (kevin bayes)":"1","importance":"0","﻿id":"3","out-degree":"7","degree":"9","eccentricity":"4.0","closeness centrality":"2.090909","eigenvector centrality":"0.13235149","barmby on marsh pc(david pridmore)":"0","controllability":"1","catchment management partnership(karen saunders)":"1","nfu (lucinda douglas)":"1","in-degree":"2","environment agency(mark reid, tom paggett)":"1","betweenness centrality":"64.564285","east yorkshire rivers trust (karen saunders)":"1"},"color":"rgb(0,0,0)","size":10.0},{"label":"*Habitat and species:rivers","x":-29.38269805908203,"y":-456.244384765625,"id":"7","attributes":{"natural england(simon christian)":"2","yorkshire water(miranda foster)":"2","yorkshire wildlife trust (kevin bayes)":"2","importance":"1","﻿id":"33","out-degree":"3","degree":"11","eccentricity":"6.0","closeness centrality":"3.5757575","eigenvector centrality":"0.625952","barmby on marsh pc(david pridmore)":"0","controllability":"1","catchment management partnership(karen saunders)":"1","nfu (lucinda douglas)":"1","in-degree":"8","environment agency(mark reid, tom paggett)":"1","betweenness centrality":"118.183334","east yorkshire rivers trust (karen saunders)":"1"},"color":"rgb(0,0,0)","size":10.0},{"label":"Agricultural Economy","x":-231.111083984375,"y":196.89422607421875,"id":"16","attributes":{"natural england(simon christian)":"2","yorkshire water(miranda foster)":"1","yorkshire wildlife trust (kevin bayes)":"1","importance":"0","﻿id":"50","out-degree":"0","degree":"0","eccentricity":"0.0","closeness centrality":"0.0","eigenvector centrality":"0.0","barmby on marsh pc(david pridmore)":"0","controllability":"1","catchment management partnership(karen saunders)":"1","nfu (lucinda douglas)":"2","in-degree":"0","environment agency(mark reid, tom paggett)":"1","betweenness centrality":"0.0","east yorkshire rivers trust (karen saunders)":"1"},"color":"rgb(0,0,0)","size":10.0},{"label":"*Nature tourism","x":191.6650390625,"y":461.59783935546875,"id":"9","attributes":{"natural england(simon christian)":"0","yorkshire water(miranda foster)":"1","yorkshire wildlife trust (kevin bayes)":"2","importance":"1","﻿id":"15","out-degree":"3","degree":"8","eccentricity":"5.0","closeness centrality":"2.8484848","eigenvector centrality":"1.0","barmby on marsh pc(david pridmore)":"0","controllability":"1","catchment management partnership(karen saunders)":"1","nfu (lucinda douglas)":"2","in-degree":"5","environment agency(mark reid, tom paggett)":"2","betweenness centrality":"474.49048","east yorkshire rivers trust (karen saunders)":"1"},"color":"rgb(0,0,0)","size":10.0},{"label":"Flood risk","x":-159.1817626953125,"y":274.146240234375,"id":"29","attributes":{"natural england(simon christian)":"1","yorkshire water(miranda foster)":"1","yorkshire wildlife trust (kevin bayes)":"1","importance":"0","﻿id":"30","out-degree":"4","degree":"6","eccentricity":"5.0","closeness centrality":"2.878788","eigenvector centrality":"0.17788436","barmby on marsh pc(david pridmore)":"0","controllability":"1","catchment management partnership(karen saunders)":"1","nfu (lucinda douglas)":"1","in-degree":"2","environment agency(mark reid, tom paggett)":"1","betweenness centrality":"47.70238","east yorkshire rivers trust (karen saunders)":"1"},"color":"rgb(0,0,0)","size":10.0},{"label":"*Boating (Navigation)","x":-458.1601867675781,"y":73.32471466064453,"id":"0","attributes":{"natural england(simon christian)":"2","yorkshire water(miranda foster)":"1","yorkshire wildlife trust (kevin bayes)":"2","importance":"1","﻿id":"17","out-degree":"0","degree":"5","eccentricity":"0.0","closeness centrality":"0.0","eigenvector centrality":"0.36842138","barmby on marsh pc(david pridmore)":"0","controllability":"1","catchment management partnership(karen saunders)":"1","nfu (lucinda douglas)":"1","in-degree":"5","environment agency(mark reid, tom paggett)":"2","betweenness centrality":"0.0","east yorkshire rivers trust (karen saunders)":"1"},"color":"rgb(0,0,0)","size":10.0},{"label":"Drainage System Management","x":85.24498748779297,"y":399.9056396484375,"id":"24","attributes":{"natural england(simon christian)":"0","yorkshire water(miranda foster)":"0","yorkshire wildlife trust (kevin bayes)":"0","importance":"0","﻿id":"39","out-degree":"6","degree":"8","eccentricity":"4.0","closeness centrality":"2.3030303","eigenvector centrality":"0.37851253","barmby on marsh pc(david pridmore)":"0","controllability":"0","catchment management partnership(karen saunders)":"0","nfu (lucinda douglas)":"0","in-degree":"2","environment agency(mark reid, tom paggett)":"0","betweenness centrality":"257.5381","east yorkshire rivers trust (karen saunders)":"0"},"color":"rgb(0,0,0)","size":10.0},{"label":"Boat moorings","x":47.68914031982422,"y":-277.193115234375,"id":"20","attributes":{"natural england(simon christian)":"2","yorkshire water(miranda foster)":"1","yorkshire wildlife trust (kevin bayes)":"1","importance":"0","﻿id":"16","out-degree":"1","degree":"1","eccentricity":"1.0","closeness centrality":"1.0","eigenvector centrality":"0.0","barmby on marsh pc(david pridmore)":"0","controllability":"1","catchment management partnership(karen saunders)":"1","nfu (lucinda douglas)":"2","in-degree":"0","environment agency(mark reid, tom paggett)":"1","betweenness centrality":"0.0","east yorkshire rivers trust (karen saunders)":"1"},"color":"rgb(0,0,0)","size":10.0},{"label":"Draining flood water in extreme events","x":-205.69696044921875,"y":57.00720977783203,"id":"26","attributes":{"natural england(simon christian)":"1","yorkshire water(miranda foster)":"1","yorkshire wildlife trust (kevin bayes)":"1","importance":"0","﻿id":"29","out-degree":"2","degree":"4","eccentricity":"7.0","closeness centrality":"4.2727275","eigenvector centrality":"0.18371578","barmby on marsh pc(david pridmore)":"0","controllability":"1","catchment management partnership(karen saunders)":"1","nfu (lucinda douglas)":"1","in-degree":"2","environment agency(mark reid, tom paggett)":"1","betweenness centrality":"7.285714","east yorkshire rivers trust (karen saunders)":"1"},"color":"rgb(0,0,0)","size":10.0},{"label":"Protected Sites Impeding Maintenance (Perception)","x":-263.7188415527344,"y":115.21808624267578,"id":"43","attributes":{"natural england(simon christian)":"0","yorkshire water(miranda foster)":"1","yorkshire wildlife trust (kevin bayes)":"1","importance":"0","﻿id":"41","out-degree":"0","degree":"0","eccentricity":"0.0","closeness centrality":"0.0","eigenvector centrality":"0.0","barmby on marsh pc(david pridmore)":"0","controllability":"1","catchment management partnership(karen saunders)":"1","nfu (lucinda douglas)":"1","in-degree":"0","environment agency(mark reid, tom paggett)":"1","betweenness centrality":"0.0","east yorkshire rivers trust (karen saunders)":"1"},"color":"rgb(0,0,0)","size":10.0},{"label":"Abstraction Reform","x":352.18524169921875,"y":162.8026123046875,"id":"15","attributes":{"natural england(simon christian)":"0","yorkshire water(miranda foster)":"0","yorkshire wildlife trust (kevin bayes)":"0","importance":"0","﻿id":"38","out-degree":"2","degree":"2","eccentricity":"5.0","closeness centrality":"3.5","eigenvector centrality":"0.0","barmby on marsh pc(david pridmore)":"0","controllability":"0","catchment management partnership(karen saunders)":"0","nfu (lucinda douglas)":"0","in-degree":"0","environment agency(mark reid, tom paggett)":"0","betweenness centrality":"0.0","east yorkshire rivers trust (karen saunders)":"0"},"color":"rgb(0,0,0)","size":10.0}],"edges":[{"source":"27","target":"32","id":"64","attributes":{},"color":"rgb(0,0,0)","size":2.0},{"source":"31","target":"32","id":"78","attributes":{},"color":"rgb(0,0,0)","size":2.0},{"source":"19","target":"17","id":"45","attributes":{},"color":"rgb(0,0,0)","size":2.0},{"source":"1","target":"7","id":"0","attributes":{},"color":"rgb(0,0,0)","size":-2.0},{"source":"26","target":"32","id":"60","attributes":{},"color":"rgb(0,0,0)","size":1.0},{"source":"14","target":"13","id":"38","attributes":{},"color":"rgb(0,0,0)","size":2.0},{"source":"21","target":"22","id":"53","attributes":{},"color":"rgb(0,0,0)","size":2.0},{"source":"9","target":"7","id":"31","attributes":{},"color":"rgb(0,0,0)","size":1.0},{"source":"11","target":"6","id":"34","attributes":{},"color":"rgb(0,0,0)","size":3.0},{"source":"29","target":"31","id":"72","attributes":{},"color":"rgb(0,0,0)","size":-2.0},{"source":"39","target":"1","id":"97","attributes":{},"color":"rgb(0,0,0)","size":2.0},{"source":"33","target":"15","id":"83","attributes":{},"color":"rgb(0,0,0)","size":1.0},{"source":"15","target":"18","id":"39","attributes":{},"color":"rgb(0,0,0)","size":1.0},{"source":"1","target":"32","id":"1","attributes":{},"color":"rgb(0,0,0)","size":-2.0},{"source":"3","target":"30","id":"12","attributes":{},"color":"rgb(0,0,0)","size":2.0},{"source":"28","target":"21","id":"69","attributes":{},"color":"rgb(0,0,0)","size":1.0},{"source":"6","target":"14","id":"19","attributes":{},"color":"rgb(0,0,0)","size":-3.0},{"source":"22","target":"20","id":"54","attributes":{},"color":"rgb(0,0,0)","size":-2.0},{"source":"7","target":"12","id":"27","attributes":{},"color":"rgb(0,0,0)","size":-2.0},{"source":"19","target":"18","id":"46","attributes":{},"color":"rgb(0,0,0)","size":2.0},{"source":"38","target":"37","id":"96","attributes":{},"color":"rgb(0,0,0)","size":1.0},{"source":"10","target":"7","id":"33","attributes":{},"color":"rgb(0,0,0)","size":1.0},{"source":"33","target":"34","id":"84","attributes":{},"color":"rgb(0,0,0)","size":2.0},{"source":"45","target":"32","id":"103","attributes":{},"color":"rgb(0,0,0)","size":2.0},{"source":"19","target":"22","id":"48","attributes":{},"color":"rgb(0,0,0)","size":2.0},{"source":"32","target":"19","id":"80","attributes":{},"color":"rgb(0,0,0)","size":-1.0},{"source":"7","target":"27","id":"28","attributes":{},"color":"rgb(0,0,0)","size":2.0},{"source":"39","target":"3","id":"99","attributes":{},"color":"rgb(0,0,0)","size":2.0},{"source":"6","target":"39","id":"24","attributes":{},"color":"rgb(0,0,0)","size":-2.0},{"source":"23","target":"24","id":"56","attributes":{},"color":"rgb(0,0,0)","size":2.0},{"source":"32","target":"34","id":"81","attributes":{},"color":"rgb(0,0,0)","size":2.0},{"source":"6","target":"5","id":"17","attributes":{},"color":"rgb(0,0,0)","size":3.0},{"source":"27","target":"39","id":"66","attributes":{},"color":"rgb(0,0,0)","size":2.0},{"source":"25","target":"26","id":"59","attributes":{},"color":"rgb(0,0,0)","size":1.0},{"source":"7","target":"11","id":"26","attributes":{},"color":"rgb(0,0,0)","size":3.0},{"source":"19","target":"15","id":"44","attributes":{},"color":"rgb(0,0,0)","size":2.0},{"source":"35","target":"27","id":"87","attributes":{},"color":"rgb(0,0,0)","size":3.0},{"source":"34","target":"15","id":"85","attributes":{},"color":"rgb(0,0,0)","size":1.0},{"source":"6","target":"8","id":"18","attributes":{},"color":"rgb(0,0,0)","size":3.0},{"source":"38","target":"7","id":"95","attributes":{},"color":"rgb(0,0,0)","size":-2.0},{"source":"6","target":"33","id":"23","attributes":{},"color":"rgb(0,0,0)","size":-2.0},{"source":"27","target":"23","id":"62","attributes":{},"color":"rgb(0,0,0)","size":2.0},{"source":"27","target":"31","id":"63","attributes":{},"color":"rgb(0,0,0)","size":2.0},{"source":"7","target":"9","id":"25","attributes":{},"color":"rgb(0,0,0)","size":1.0},{"source":"1","target":"33","id":"2","attributes":{},"color":"rgb(0,0,0)","size":-2.0},{"source":"3","target":"1","id":"8","attributes":{},"color":"rgb(0,0,0)","size":2.0},{"source":"20","target":"15","id":"49","attributes":{},"color":"rgb(0,0,0)","size":2.0},{"source":"33","target":"12","id":"82","attributes":{},"color":"rgb(0,0,0)","size":2.0},{"source":"35","target":"13","id":"86","attributes":{},"color":"rgb(0,0,0)","size":3.0},{"source":"19","target":"21","id":"47","attributes":{},"color":"rgb(0,0,0)","size":2.0},{"source":"11","target":"27","id":"35","attributes":{},"color":"rgb(0,0,0)","size":3.0},{"source":"3","target":"29","id":"11","attributes":{},"color":"rgb(0,0,0)","size":2.0},{"source":"28","target":"17","id":"68","attributes":{},"color":"rgb(0,0,0)","size":-2.0},{"source":"27","target":"6","id":"61","attributes":{},"color":"rgb(0,0,0)","size":2.0},{"source":"8","target":"7","id":"30","attributes":{},"color":"rgb(0,0,0)","size":2.0},{"source":"29","target":"32","id":"73","attributes":{},"color":"rgb(0,0,0)","size":1.0},{"source":"35","target":"32","id":"89","attributes":{},"color":"rgb(0,0,0)","size":2.0},{"source":"22","target":"32","id":"55","attributes":{},"color":"rgb(0,0,0)","size":-2.0},{"source":"27","target":"33","id":"65","attributes":{},"color":"rgb(0,0,0)","size":2.0},{"source":"2","target":"32","id":"5","attributes":{},"color":"rgb(0,0,0)","size":2.0},{"source":"7","target":"37","id":"29","attributes":{},"color":"rgb(0,0,0)","size":-2.0},{"source":"6","target":"29","id":"22","attributes":{},"color":"rgb(0,0,0)","size":1.0},{"source":"9","target":"12","id":"32","attributes":{},"color":"rgb(0,0,0)","size":2.0},{"source":"12","target":"21","id":"36","attributes":{},"color":"rgb(0,0,0)","size":2.0},{"source":"39","target":"31","id":"102","attributes":{},"color":"rgb(0,0,0)","size":2.0},{"source":"6","target":"17","id":"20","attributes":{},"color":"rgb(0,0,0)","size":2.0},{"source":"13","target":"12","id":"37","attributes":{},"color":"rgb(0,0,0)","size":2.0},{"source":"30","target":"23","id":"74","attributes":{},"color":"rgb(0,0,0)","size":2.0},{"source":"3","target":"33","id":"13","attributes":{},"color":"rgb(0,0,0)","size":1.0},{"source":"30","target":"27","id":"76","attributes":{},"color":"rgb(0,0,0)","size":2.0},{"source":"39","target":"2","id":"98","attributes":{},"color":"rgb(0,0,0)","size":-2.0},{"source":"15","target":"20","id":"40","attributes":{},"color":"rgb(0,0,0)","size":-1.0},{"source":"35","target":"33","id":"90","attributes":{},"color":"rgb(0,0,0)","size":2.0},{"source":"25","target":"17","id":"58","attributes":{},"color":"rgb(0,0,0)","size":2.0},{"source":"32","target":"15","id":"79","attributes":{},"color":"rgb(0,0,0)","size":2.0},{"source":"18","target":"22","id":"43","attributes":{},"color":"rgb(0,0,0)","size":2.0},{"source":"5","target":"7","id":"16","attributes":{},"color":"rgb(0,0,0)","size":2.0},{"source":"28","target":"12","id":"67","attributes":{},"color":"rgb(0,0,0)","size":-2.0},{"source":"28","target":"22","id":"70","attributes":{},"color":"rgb(0,0,0)","size":1.0},{"source":"4","target":"3","id":"15","attributes":{},"color":"rgb(0,0,0)","size":2.0},{"source":"2","target":"37","id":"7","attributes":{},"color":"rgb(0,0,0)","size":1.0},{"source":"20","target":"18","id":"50","attributes":{},"color":"rgb(0,0,0)","size":2.0},{"source":"2","target":"7","id":"4","attributes":{},"color":"rgb(0,0,0)","size":2.0},{"source":"39","target":"30","id":"101","attributes":{},"color":"rgb(0,0,0)","size":1.0},{"source":"39","target":"28","id":"100","attributes":{},"color":"rgb(0,0,0)","size":2.0},{"source":"35","target":"28","id":"88","attributes":{},"color":"rgb(0,0,0)","size":-2.0},{"source":"35","target":"34","id":"91","attributes":{},"color":"rgb(0,0,0)","size":1.0},{"source":"2","target":"33","id":"6","attributes":{},"color":"rgb(0,0,0)","size":2.0},{"source":"16","target":"17","id":"42","attributes":{},"color":"rgb(0,0,0)","size":2.0},{"source":"30","target":"36","id":"77","attributes":{},"color":"rgb(0,0,0)","size":2.0},{"source":"21","target":"20","id":"52","attributes":{},"color":"rgb(0,0,0)","size":-2.0},{"source":"30","target":"24","id":"75","attributes":{},"color":"rgb(0,0,0)","size":-2.0},{"source":"37","target":"27","id":"94","attributes":{},"color":"rgb(0,0,0)","size":2.0},{"source":"20","target":"21","id":"51","attributes":{},"color":"rgb(0,0,0)","size":2.0},{"source":"1","target":"37","id":"3","attributes":{},"color":"rgb(0,0,0)","size":-1.0},{"source":"6","target":"25","id":"21","attributes":{},"color":"rgb(0,0,0)","size":3.0},{"source":"23","target":"28","id":"57","attributes":{},"color":"rgb(0,0,0)","size":1.0},{"source":"15","target":"27","id":"41","attributes":{},"color":"rgb(0,0,0)","size":2.0},{"source":"3","target":"7","id":"10","attributes":{},"color":"rgb(0,0,0)","size":1.0},{"source":"45","target":"33","id":"104","attributes":{},"color":"rgb(0,0,0)","size":2.0},{"source":"3","target":"37","id":"14","attributes":{},"color":"rgb(0,0,0)","size":2.0},{"source":"28","target":"33","id":"71","attributes":{},"color":"rgb(0,0,0)","size":-2.0},{"source":"36","target":"6","id":"92","attributes":{},"color":"rgb(0,0,0)","size":2.0},{"source":"36","target":"32","id":"93","attributes":{},"color":"rgb(0,0,0)","size":1.0},{"source":"3","target":"6","id":"9","attributes":{},"color":"rgb(0,0,0)","size":3.0}]}